csaf/__init__.py
csaf/__main__.py
csaf/category.py
csaf/cli.py
csaf/config.py
csaf/cpe.py
csaf/csaf.py
csaf/cve.py
csaf/cvss.py
csaf/cwe.py
csaf/definitions.py
csaf/document.py
csaf/env.py
csaf/hash.py
csaf/product.py
csaf/purl.py
csaf/terminal.py
csaf/tlp.py
csaf/version.py
csaf/vuln_types.py
csaf/vulnerability.py
csaf/mandatory/__init__.py
csaf/mandatory/acyclic_product_ids.py
csaf/mandatory/consistent_product_status.py
csaf/mandatory/defined_group_ids.py
csaf/mandatory/defined_product_ids.py
csaf/mandatory/rules.py
csaf/mandatory/translator_and_source_lang.py
csaf/mandatory/unique_group_ids.py
csaf/mandatory/unique_product_ids.py
csaf/mandatory/valid_category_name.py
csaf-2025.10.2.dist-info/licenses/LICENSE
csaf-2025.10.2.dist-info/METADATA
csaf-2025.10.2.dist-info/WHEEL
csaf-2025.10.2.dist-info/entry_points.txt
csaf-2025.10.2.dist-info/top_level.txt
csaf-2025.10.2.dist-info/RECORD
