Metadata-Version: 2.4
Name: csaf
Version: 2025.10.2
Summary: Common Security Advisory Framework (CSAF) Verification, Validation, and Application Programming Interface (API).
Author-email: Stefan Hagen <stefan@hagen.link>
Maintainer-email: Stefan Hagen <stefan@hagen.link>
License-Expression: MIT
Project-URL: Homepage, https://git.sr.ht/~sthagen/csaf
Project-URL: Bug-Tracker, https://todo.sr.ht/~sthagen/csaf
Project-URL: Documentation, https://codes.dilettant.life/docs/csaf
Project-URL: Source-Code, https://git.sr.ht/~sthagen/csaf
Project-URL: Test-Coverage, https://codes.dilettant.life/coverage/csaf
Keywords: code-generation,developer-tools,validation,verification
Classifier: Development Status :: 3 - Alpha
Classifier: Intended Audience :: Developers
Classifier: Programming Language :: Python :: 3.10
Classifier: Programming Language :: Python :: 3.11
Classifier: Programming Language :: Python :: 3.12
Classifier: Programming Language :: Python :: 3.13
Classifier: Programming Language :: Python :: 3.9
Classifier: Topic :: Software Development :: Build Tools
Classifier: Topic :: Software Development :: Libraries
Requires-Python: >=3.9
License-File: LICENSE
Requires-Dist: jmespath>=1.0.1
Requires-Dist: jsonschema>=4.23.0
Requires-Dist: langcodes>=3.5.0
Requires-Dist: lazr.uri>=1.0.7
Requires-Dist: msgspec>=0.18.6
Requires-Dist: pydantic>=2.10.3
Requires-Dist: referencing>=0.35.1
Requires-Dist: scooby>=0.10.0
Requires-Dist: setuptools>=75.6.0
Requires-Dist: typer>=0.15.1
Provides-Extra: dev
Requires-Dist: black; extra == "dev"
Requires-Dist: coverage; extra == "dev"
Requires-Dist: hypothesis; extra == "dev"
Requires-Dist: mypy; extra == "dev"
Requires-Dist: pytest; extra == "dev"
Requires-Dist: pytest-cov; extra == "dev"
Requires-Dist: pytest-flake8; extra == "dev"
Requires-Dist: ruff; extra == "dev"
Dynamic: license-file
